hinoki/Untitled-2
hinoki/Untitled-3
hinoki/__init__.py
hinoki/assets.py
hinoki/cli.py
hinoki/config.py
hinoki/import_definitions.py
hinoki/initialize_cluster.py
hinoki/logger.py
hinoki/sensuapi.py
hinoki/sensuasset.py
hinoki/update_default_password.py
hinoki/validate.py
hinoki-0.0.2.dist-info/AUTHORS.rst
hinoki-0.0.2.dist-info/LICENSE.txt
hinoki-0.0.2.dist-info/METADATA
hinoki-0.0.2.dist-info/WHEEL
hinoki-0.0.2.dist-info/entry_points.txt
hinoki-0.0.2.dist-info/top_level.txt
hinoki-0.0.2.dist-info/RECORD
